[{"__symbolic":"module","version":4,"metadata":{"WeatherCurrentWindComponent":{"__symbolic":"class","decorators":[{"__symbolic":"call","expression":{"__symbolic":"reference","module":"@angular/core","name":"Component","line":10,"character":1},"arguments":[{"selector":"weather-current-wind","changeDetection":{"__symbolic":"select","expression":{"__symbolic":"reference","module":"@angular/core","name":"ChangeDetectionStrategy","line":12,"character":19},"member":"OnPush"},"styles":["\n      :host {\n        display: flex;\n        justify-content: space-around;\n        align-items: center;\n        font-size: 0.8em;\n        min-height: 1.3em;\n      }\n      i {\n        margin-left: 0.3em;\n        font-size: 1.6em;\n      }\n    "],"template":"\n    <span>Wind {{ speed }} {{ unit }}</span>\n    <i [class]=\"windIcon\"></i>\n  "}]}],"members":{"scale":[{"__symbolic":"property","decorators":[{"__symbolic":"call","expression":{"__symbolic":"reference","module":"@angular/core","name":"Input","line":39,"character":3}}]}],"deg":[{"__symbolic":"property","decorators":[{"__symbolic":"call","expression":{"__symbolic":"reference","module":"@angular/core","name":"Input","line":49,"character":3}}]}],"speed":[{"__symbolic":"property","decorators":[{"__symbolic":"call","expression":{"__symbolic":"reference","module":"@angular/core","name":"Input","line":58,"character":3}}]}],"mapScaleToText":[{"__symbolic":"method"}]}}}}]